odoo/addons/l10n_ch_scan_bvr/README.rst
odoo/addons/l10n_ch_scan_bvr/__init__.py
odoo/addons/l10n_ch_scan_bvr/__manifest__.py
odoo/addons/l10n_ch_scan_bvr/i18n/am.po
odoo/addons/l10n_ch_scan_bvr/i18n/ar.po
odoo/addons/l10n_ch_scan_bvr/i18n/bg.po
odoo/addons/l10n_ch_scan_bvr/i18n/bs.po
odoo/addons/l10n_ch_scan_bvr/i18n/ca.po
odoo/addons/l10n_ch_scan_bvr/i18n/ca_ES.po
odoo/addons/l10n_ch_scan_bvr/i18n/cs.po
odoo/addons/l10n_ch_scan_bvr/i18n/da.po
odoo/addons/l10n_ch_scan_bvr/i18n/de.po
odoo/addons/l10n_ch_scan_bvr/i18n/el_GR.po
odoo/addons/l10n_ch_scan_bvr/i18n/en_GB.po
odoo/addons/l10n_ch_scan_bvr/i18n/es.po
odoo/addons/l10n_ch_scan_bvr/i18n/es_AR.po
odoo/addons/l10n_ch_scan_bvr/i18n/es_CO.po
odoo/addons/l10n_ch_scan_bvr/i18n/es_CR.po
odoo/addons/l10n_ch_scan_bvr/i18n/es_DO.po
odoo/addons/l10n_ch_scan_bvr/i18n/es_EC.po
odoo/addons/l10n_ch_scan_bvr/i18n/es_ES.po
odoo/addons/l10n_ch_scan_bvr/i18n/es_MX.po
odoo/addons/l10n_ch_scan_bvr/i18n/es_PE.po
odoo/addons/l10n_ch_scan_bvr/i18n/es_VE.po
odoo/addons/l10n_ch_scan_bvr/i18n/et.po
odoo/addons/l10n_ch_scan_bvr/i18n/eu.po
odoo/addons/l10n_ch_scan_bvr/i18n/fa.po
odoo/addons/l10n_ch_scan_bvr/i18n/fi.po
odoo/addons/l10n_ch_scan_bvr/i18n/fr.po
odoo/addons/l10n_ch_scan_bvr/i18n/fr_CH.po
odoo/addons/l10n_ch_scan_bvr/i18n/gl.po
odoo/addons/l10n_ch_scan_bvr/i18n/gl_ES.po
odoo/addons/l10n_ch_scan_bvr/i18n/he.po
odoo/addons/l10n_ch_scan_bvr/i18n/hr.po
odoo/addons/l10n_ch_scan_bvr/i18n/hr_HR.po
odoo/addons/l10n_ch_scan_bvr/i18n/hu.po
odoo/addons/l10n_ch_scan_bvr/i18n/id.po
odoo/addons/l10n_ch_scan_bvr/i18n/it.po
odoo/addons/l10n_ch_scan_bvr/i18n/ja.po
odoo/addons/l10n_ch_scan_bvr/i18n/ko.po
odoo/addons/l10n_ch_scan_bvr/i18n/l10n_ch_scan_bvr.pot
odoo/addons/l10n_ch_scan_bvr/i18n/lt.po
odoo/addons/l10n_ch_scan_bvr/i18n/lv.po
odoo/addons/l10n_ch_scan_bvr/i18n/mk.po
odoo/addons/l10n_ch_scan_bvr/i18n/mn.po
odoo/addons/l10n_ch_scan_bvr/i18n/nb.po
odoo/addons/l10n_ch_scan_bvr/i18n/nb_NO.po
odoo/addons/l10n_ch_scan_bvr/i18n/nl.po
odoo11_addon_l10n_ch_scan_bvr-11.0.1.0.0.99.dev8.dist-info/METADATA
odoo11_addon_l10n_ch_scan_bvr-11.0.1.0.0.99.dev8.dist-info/WHEEL
odoo11_addon_l10n_ch_scan_bvr-11.0.1.0.0.99.dev8.dist-info/top_level.txt
odoo11_addon_l10n_ch_scan_bvr-11.0.1.0.0.99.dev8.dist-info/RECORD
